{"description":"MARC 21 Format for Bibliographic Data.","fields":{"LDR":{"repeatable":false,"positions":{"00-04":{"label":"Record length","url":"https://www.loc.gov/marc/bibliographic/bdleader.html"},"05":{"label":"Record status","url":"https://www.loc.gov/marc/bibliographic/bdleader.html","codes":{"a":{"label":"Increase in encoding level"},"c":{"label":"Corrected or revised"},"d":{"label":"Deleted"},"n":{"label":"New"},"p":{"label":"Increase in encoding level from prepublication"}}},"06":{"label":"Type of record","url":"https://www.loc.gov/marc/bibliographic/bdleader.html","codes":{"a":{"label":"Language material"},"c":{"label":"Notated music"},"d":{"label":"Manuscript notated music"},"e":{"label":"Cartographic material"},"f":{"label":"Manuscript cartographic material"},"g":{"label":"Projected medium"},"i":{"label":"Nonmusical sound recording"},"j":{"label":"Musical sound recording"},"k":{"label":"Two-dimensional nonprojectable graphic"},"m":{"label":"Computer file"},"o":{"label":"Kit"},"p":{"label":"Mixed materials"},"r":{"label":"Three-dimensional artifact or naturally occurring object"},"t":{"label":"Manuscript language material"}},"historical-codes":{"b":{"label":"Archival and manuscripts control [OBSOLETE, 1995]"},"h":{"label":"Microform publications [OBSOLETE, 1972] [USMARC only]"},"n":{"label":"Special instructional material"}}},"07":{"label":"Bibliographic level","url":"https://www.loc.gov/marc/bibliographic/bdleader.html","codes":{"a":{"label":"Monographic component part"},"b":{"label":"Serial component part"},"c":{"label":"Collection"},"d":{"label":"Subunit"},"i":{"label":"Integrating resource"},"m":{"label":"Monograph/Item"},"s":{"label":"Serial"}},"historical-codes":{"p":{"label":"Pamphlet [OBSOLETE, 1988] [CAN/MARC only]"}}},"08":{"label":"Type of control","url":"https://www.loc.gov/marc/bibliographic/bdleader.html","codes":{" ":{"label":"No specified type"},"a":{"label":"Archival"}}},"09":{"label":"Character coding scheme","url":"https://www.loc.gov/marc/bibliographic/bdleader.html","codes":{" ":{"label":"MARC-8"},"a":{"label":"UCS/Unicode"}}},"10":{"label":"Indicator count","url":"https://www.loc.gov/marc/bibliographic/bdleader.html"},"11":{"label":"Subfield code count","url":"https://www.loc.gov/marc/bibliographic/bdleader.html"},"12-16":{"label":"Base address of data","url":"https://www.loc.gov/marc/bibliographic/bdleader.html"},"17":{"label":"Encoding level","url":"https://www.loc.gov/marc/bibliographic/bdleader.html","codes":{" ":{"label":"Full level"},"1":{"label":"Full level, material not examined"},"2":{"label":"Less-than-full level, material not examined"},"3":{"label":"Abbreviated level"},"4":{"label":"Core level"},"5":{"label":"Partial (preliminary) level"},"7":{"label":"Minimal level"},"8":{"label":"Prepublication level"},"u":{"label":"Unknown"},"z":{"label":"Not applicable"}},"historical-codes":{"0":{"label":"Full level with item [OBSOLETE, 1997] [CAN/MARC only]"},"6":{"label":"Minimal level [OBSOLETE, 1997] [CAN/MARC only]"}}},"18":{"label":"Descriptive cataloging form","url":"https://www.loc.gov/marc/bibliographic/bdleader.html","codes":{" ":{"label":"Non-ISBD"},"a":{"label":"AACR 2"},"c":{"label":"ISBD punctuation omitted"},"i":{"label":"ISBD punctuation included"},"n":{"label":"Non-ISBD punctuation omitted"},"u":{"label":"Unknown"}},"historical-codes":{"p":{"label":"Record is in partial ISBD form [OBSOLETE, 1987]"},"r":{"label":"Record is in provisional form [OBSOLETE, 1981]"}}},"19":{"label":"Multipart resource record level","url":"https://www.loc.gov/marc/bibliographic/bdleader.html","codes":{" ":{"label":"Not specified or not applicable"},"a":{"label":"Set"},"b":{"label":"Part with independent title"},"c":{"label":"Part with dependent title"}},"historical-codes":{"r":{"label":"Linked record requirement [OBSOLETE, 2007]"},"2":{"label":"Open entry for a collection [OBSOLETE, 1984] [CAN/MARC only]"}}},"20":{"label":"Length of the length-of-field portion","url":"https://www.loc.gov/marc/bibliographic/bdleader.html"},"21":{"label":"Length of the starting-character-position portion","url":"https://www.loc.gov/marc/bibliographic/bdleader.html"},"22":{"label":"Length of the implementation-defined portion","url":"https://www.loc.gov/marc/bibliographic/bdleader.html"}}},"020":{"tag":"020","label":"International Standard Book Number","url":"https://www.loc.gov/marc/bibliographic/bd020.html","repeatable":true,"indicator1":null,"indicator2":null,"subfields":{"a":{"label":"International Standard Book Number","repeatable":false},"c":{"label":"Terms of availability","repeatable":false},"q":{"label":"Qualifying information","repeatable":true},"z":{"label":"Canceled/invalid ISBN","repeatable":true},"6":{"label":"Linkage","repeatable":false},"8":{"label":"Field link and sequence number","repeatable":true}},"historical-subfields":{"b":{"label":"Binding information (BK, MP, MU) [OBSOLETE]"}}},"100":{"tag":"100","label":"Main Entry - Personal Name","url":"https://www.loc.gov/marc/bibliographic/bd100.html","repeatable":false,"indicator1":{"label":"Type of personal name entry element","codes":{"0":{"label":"Forename"},"1":{"label":"Surname"},"3":{"label":"Family name"}}},"indicator2":null,"subfields":{"a":{"label":"Personal name","repeatable":false},"b":{"label":"Numeration","repeatable":false},"c":{"label":"Titles and words associated with a name","repeatable":true},"d":{"label":"Dates associated with a name","repeatable":false},"e":{"label":"Relator term","repeatable":true},"f":{"label":"Date of a work","repeatable":false},"g":{"label":"Miscellaneous information","repeatable":true},"j":{"label":"Attribution qualifier","repeatable":true},"k":{"label":"Form subheading","repeatable":true},"l":{"label":"Language of a work","repeatable":false},"n":{"label":"Number of part/section of a work","repeatable":true},"p":{"label":"Name of part/section of a work","repeatable":true},"q":{"label":"Fuller form of name","repeatable":false},"t":{"label":"Title of a work","repeatable":false},"u":{"label":"Affiliation","repeatable":false},"0":{"label":"Authority record control number or standard number","repeatable":true},"4":{"label":"Relator code","repeatable":true,"codelist":{"name":"MARC Code List for Relators","url":"https://www.loc.gov/marc/relators/relaterm.html"}},"6":{"label":"Linkage","repeatable":false},"8":{"label":"Field link and sequence number","repeatable":true}}},"110":{"tag":"110","label":"Main Entry - Corporate Name","url":"https://www.loc.gov/marc/bibliographic/bd110.html","repeatable":false,"indicator1":{"label":"Type of corporate name entry element","codes":{"0":{"label":"Inverted name"},"1":{"label":"Jurisdiction name"},"2":{"label":"Name in direct order"}}},"indicator2":null,"subfields":{"a":{"label":"Corporate name or jurisdiction name as entry element","repeatable":false},"b":{"label":"Subordinate unit","repeatable":true},"c":{"label":"Location of meeting","repeatable":true},"d":{"label":"Date of meeting or treaty signing","repeatable":true},"e":{"label":"Relator term","repeatable":true},"f":{"label":"Date of a work","repeatable":false},"g":{"label":"Miscellaneous information","repeatable":true},"k":{"label":"Form subheading","repeatable":true},"l":{"label":"Language of a work","repeatable":false},"n":{"label":"Number of part/section/meeting","repeatable":true},"p":{"label":"Name of part/section of a work","repeatable":true},"t":{"label":"Title of a work","repeatable":false},"u":{"label":"Affiliation","repeatable":false},"0":{"label":"Authority record control number or standard number","repeatable":true},"4":{"label":"Relator code","repeatable":true,"codelist":{"name":"MARC Code List for Relators","url":"https://www.loc.gov/marc/relators/relaterm.html"}},"6":{"label":"Linkage","repeatable":false},"8":{"label":"Field link and sequence number","repeatable":true}}},"111":{"tag":"111","label":"Main Entry - Meeting Name","url":"https://www.loc.gov/marc/bibliographic/bd111.html","repeatable":false,"indicator1":{"label":"Type of meeting name entry element","codes":{"0":{"label":"Inverted name"},"1":{"label":"Jurisdiction name"},"2":{"label":"Name in direct order"}}},"indicator2":null,"subfields":{"a":{"label":"Meeting name or jurisdiction name as entry element","repeatable":false},"c":{"label":"Location of meeting","repeatable":true},"d":{"label":"Date of meeting","repeatable":false},"e":{"label":"Subordinate unit","repeatable":true},"f":{"label":"Date of a work","repeatable":false},"g":{"label":"Miscellaneous information","repeatable":true},"j":{"label":"Relator term","repeatable":true},"k":{"label":"Form subheading","repeatable":true},"l":{"label":"Language of a work","repeatable":false},"n":{"label":"Number of part/section/meeting","repeatable":true},"p":{"label":"Name of part/section of a work","repeatable":true},"q":{"label":"Name of meeting following jurisdiction name entry element","repeatable":false},"t":{"label":"Title of a work","repeatable":false},"u":{"label":"Affiliation","repeatable":false},"0":{"label":"Authority record control number or standard number","repeatable":true},"4":{"label":"Relationship","repeatable":true,"codelist":{"name":"MARC Code List for Relators","url":"https://www.loc.gov/marc/relators/relaterm.html"}},"6":{"label":"Linkage","repeatable":false},"8":{"label":"Field link and sequence number","repeatable":true}}},"245":{"tag":"245","label":"Title Statement","url":"https://www.loc.gov/marc/bibliographic/bd245.html","repeatable":false,"indicator1":{"label":"Title added entry","codes":{"0":{"label":"No added entry"},"1":{"label":"Added entry"}}},"indicator2":{"label":"Nonfiling characters","codes":{"0":{"label":"No nonfiling characters"},"1-9":{"label":"Number of nonfiling characters"}}},"subfields":{"a":{"label":"Title","repeatable":false},"b":{"label":"Remainder of title","repeatable":false},"c":{"label":"Statement of responsibility, etc.","repeatable":false},"f":{"label":"Inclusive dates","repeatable":false},"g":{"label":"Bulk dates","repeatable":false},"h":{"label":"Medium","repeatable":false},"k":{"label":"Form","repeatable":true},"n":{"label":"Number of part/section of a work","repeatable":true},"p":{"label":"Name of part/section of a work","repeatable":true},"s":{"label":"Version","repeatable":false},"6":{"label":"Linkage","repeatable":false},"8":{"label":"Field link and sequence number","repeatable":true}},"historical-subfields":{"d":{"label":"Designation of section/part/series (SE) [OBSOLETE, 1979]"},"e":{"label":"Name of part/section/series (SE) [OBSOLETE, 1979]"}}},"250":{"tag":"250","label":"Edition Statement","url":"https://www.loc.gov/marc/bibliographic/bd250.html","repeatable":true,"indicator1":null,"indicator2":null,"subfields":{"a":{"label":"Edition statement","repeatable":false},"b":{"label":"Remainder of edition statement","repeatable":false},"3":{"label":"Materials specified","repeatable":false},"6":{"label":"Linkage","repeatable":false},"8":{"label":"Field link and sequence number","repeatable":true}}},"264":{"tag":"264","label":"Production, Publication, Distribution, Manufacture, and Copyright Notice","url":"https://www.loc.gov/marc/bibliographic/bd264.html","repeatable":true,"indicator1":{"label":"Sequence of statements","codes":{" ":{"label":"Not applicable/No information provided/Earliest"},"2":{"label":"Intervening"},"3":{"label":"Current/Latest"}}},"indicator2":{"label":"Function of entity","codes":{"0":{"label":"Production"},"1":{"label":"Publication"},"2":{"label":"Distribution"},"3":{"label":"Manufacture"},"4":{"label":"Copyright notice date"}}},"subfields":{"a":{"label":"Place of production, publication, distribution, manufacture","repeatable":true},"b":{"label":"Name of producer, publisher, distributor, manufacturer","repeatable":true},"c":{"label":"Date of production, publication, distribution, manufacture, or copyright notice","repeatable":true},"3":{"label":"Materials specified","repeatable":false},"6":{"label":"Linkage","repeatable":false},"8":{"label":"Field link and sequence number","repeatable":true}}},"300":{"tag":"300","label":"Physical Description","url":"https://www.loc.gov/marc/bibliographic/bd300.html","repeatable":true,"indicator1":null,"indicator2":null,"subfields":{"a":{"label":"Extent","repeatable":true},"b":{"label":"Other physical details","repeatable":false},"c":{"label":"Dimensions","repeatable":true},"e":{"label":"Accompanying material","repeatable":false},"f":{"label":"Type of unit","repeatable":true},"g":{"label":"Size of unit","repeatable":true},"3":{"label":"Materials specified","repeatable":false},"6":{"label":"Linkage","repeatable":false},"8":{"label":"Field link and sequence number","repeatable":true}},"historical-subfields":{"d":{"label":"Accompanying material [OBSOLETE, 1997] [CAN/MARC only]"},"m":{"label":"Identification/manufacturer number [pre-AACR2 records only] [OBSOLETE, 1988] [CAN/MARC only]"},"n":{"label":"Matrix and/or take number [Sound recordings, pre-AACR2 records only] [OBSOLETE, 1988] [CAN/MARC only]"}}},"338":{"tag":"338","label":"Carrier Type","url":"https://www.loc.gov/marc/bibliographic/bd338.html","repeatable":true,"indicator1":null,"indicator2":null,"subfields":{"a":{"label":"Carrier type term","repeatable":true},"b":{"label":"Carrier type code","repeatable":true},"0":{"label":"Authority record control number or standard number","repeatable":true},"2":{"label":"Source","repeatable":false,"codelist":{"name":"Genre/Form Code and Term Source Codes","url":"http://www.loc.gov/standards/sourcelist/genre-form.html"}},"3":{"label":"Materials specified","repeatable":false},"6":{"label":"Linkage","repeatable":false},"8":{"label":"Field link and sequence number","repeatable":true}}},"490":{"tag":"490","label":"Series Statement","url":"https://www.loc.gov/marc/bibliographic/bd490.html","repeatable":true,"indicator1":{"label":"Series tracing policy","codes":{"0":{"label":"Series not traced"},"1":{"label":"Series traced"}}},"indicator2":null,"subfields":{"a":{"label":"Series statement","repeatable":true},"l":{"label":"Library of Congress call number","repeatable":false},"v":{"label":"Volume/sequential designation","repeatable":true},"x":{"label":"International Standard Serial Number","repeatable":true},"3":{"label":"Materials specified","repeatable":false},"6":{"label":"Linkage","repeatable":false},"8":{"label":"Field link and sequence number","repeatable":true}}},"700":{"tag":"700","label":"Added Entry - Personal Name","url":"https://www.loc.gov/marc/bibliographic/bd700.html","repeatable":true,"indicator1":{"label":"Type of personal name entry element","codes":{"0":{"label":"Forename"},"1":{"label":"Surname"},"3":{"label":"Family name"}}},"indicator2":{"label":"Type of added entry","codes":{" ":{"label":"No information provided"},"2":{"label":"Analytical entry"}}},"subfields":{"a":{"label":"Personal name","repeatable":false},"b":{"label":"Numeration","repeatable":false},"c":{"label":"Titles and other words associated with a name","repeatable":true},"d":{"label":"Dates associated with a name","repeatable":false},"e":{"label":"Relator term","repeatable":true},"f":{"label":"Date of a work","repeatable":false},"g":{"label":"Miscellaneous information","repeatable":true},"h":{"label":"Medium","repeatable":false},"i":{"label":"Relationship information","repeatable":true},"j":{"label":"Attribution qualifier","repeatable":true},"k":{"label":"Form subheading","repeatable":true},"l":{"label":"Language of a work","repeatable":false},"m":{"label":"Medium of performance for music","repeatable":true},"n":{"label":"Number of part/section of a work","repeatable":true},"o":{"label":"Arranged statement for music","repeatable":false},"p":{"label":"Name of part/section of a work","repeatable":true},"q":{"label":"Fuller form of name","repeatable":false},"r":{"label":"Key for music","repeatable":false},"s":{"label":"Version","repeatable":false},"t":{"label":"Title of a work","repeatable":false},"u":{"label":"Affiliation","repeatable":false},"x":{"label":"International Standard Serial Number","repeatable":false},"0":{"label":"Authority record control number or standard number","repeatable":true},"3":{"label":"Materials specified","repeatable":false},"4":{"label":"Relationship","repeatable":true,"codelist":{"name":"MARC Code List for Relators","url":"https://www.loc.gov/marc/relators/relaterm.html"}},"5":{"label":"Institution to which field applies","repeatable":false},"6":{"label":"Linkage","repeatable":false},"8":{"label":"Field link and sequence number","repeatable":true}}},"710":{"tag":"710","label":"Added Entry - Corporate Name","url":"https://www.loc.gov/marc/bibliographic/bd710.html","repeatable":true,"indicator1":{"label":"Type of corporate name entry element","codes":{"0":{"label":"Inverted name"},"1":{"label":"Jurisdiction name"},"2":{"label":"Name in direct order"}}},"indicator2":{"label":"Type of added entry","codes":{" ":{"label":"No information provided"},"2":{"label":"Analytical entry"}}},"subfields":{"a":{"label":"Corporate name or jurisdiction name as entry element","repeatable":false},"b":{"label":"Subordinate unit","repeatable":true},"c":{"label":"Location of meeting","repeatable":true},"d":{"label":"Date of meeting or treaty signing","repeatable":true},"e":{"label":"Relator term","repeatable":true},"f":{"label":"Date of a work","repeatable":false},"g":{"label":"Miscellaneous information","repeatable":true},"h":{"label":"Medium","repeatable":false},"i":{"label":"Relationship information","repeatable":true},"k":{"label":"Form subheading","repeatable":true},"l":{"label":"Language of a work","repeatable":false},"m":{"label":"Medium of performance for music","repeatable":true},"n":{"label":"Number of part/section/meeting","repeatable":true},"o":{"label":"Arranged statement for music","repeatable":false},"p":{"label":"Name of part/section of a work","repeatable":true},"r":{"label":"Key for music","repeatable":false},"s":{"label":"Version","repeatable":false},"t":{"label":"Title of a work","repeatable":false},"u":{"label":"Affiliation","repeatable":false},"x":{"label":"International Standard Serial Number","repeatable":false},"0":{"label":"Authority record control number or standard number","repeatable":true},"3":{"label":"Materials specified","repeatable":false},"4":{"label":"Relationship","repeatable":true,"codelist":{"name":"MARC Code List for Relators","url":"https://www.loc.gov/marc/relators/relaterm.html"}},"5":{"label":"Institution to which field applies","repeatable":false},"6":{"label":"Linkage","repeatable":false},"8":{"label":"Field link and sequence number","repeatable":true}}},"711":{"tag":"711","label":"Added Entry - Meeting Name","url":"https://www.loc.gov/marc/bibliographic/bd711.html","repeatable":true,"indicator1":{"label":"Type of meeting name entry element","codes":{"0":{"label":"Inverted name"},"1":{"label":"Jurisdiction name"},"2":{"label":"Name in direct order"}}},"indicator2":{"label":"Type of added entry","codes":{" ":{"label":"No information provided"},"2":{"label":"Analytical entry"}}},"subfields":{"a":{"label":"Meeting name or jurisdiction name as entry element","repeatable":false},"c":{"label":"Location of meeting","repeatable":true},"d":{"label":"Date of meeting","repeatable":false},"e":{"label":"Subordinate unit","repeatable":true},"f":{"label":"Date of a work","repeatable":false},"g":{"label":"Miscellaneous information","repeatable":true},"h":{"label":"Medium","repeatable":false},"i":{"label":"Relationship information","repeatable":true},"j":{"label":"Relator term","repeatable":true},"k":{"label":"Form subheading","repeatable":true},"l":{"label":"Language of a work","repeatable":false},"n":{"label":"Number of part/section/meeting","repeatable":true},"p":{"label":"Name of part/section of a work","repeatable":true},"q":{"label":"Name of meeting following jurisdiction name entry element","repeatable":false},"s":{"label":"Version","repeatable":false},"t":{"label":"Title of a work","repeatable":false},"u":{"label":"Affiliation","repeatable":false},"x":{"label":"International Standard Serial Number","repeatable":false},"0":{"label":"Authority record control number or standard number","repeatable":true},"3":{"label":"Materials specified","repeatable":false},"4":{"label":"Relationship","repeatable":true,"codelist":{"name":"MARC Code List for Relators","url":"https://www.loc.gov/marc/relators/relaterm.html"}},"5":{"label":"Institution to which field applies","repeatable":false},"6":{"label":"Linkage","repeatable":false},"8":{"label":"Field link and sequence number","repeatable":true}}}}}